{"cameraMode":{"drawMode":0,"name":"Shaded","section":"Shading Mode"},"sceneLighting":true,"audioPlay":false,"sceneViewState":{"m_AlwaysRefresh":false,"showFog":true,"showSkybox":true,"showFlares":true,"showImageEffects":true,"showParticleSystems":true,"showVisualEffectGraphs":true,"m_FxEnabled":true},"in2DMode":false,"pivot":{"x":169.29774475097657,"y":8.259737014770508,"z":560.2039794921875},"rotation":{"x":-0.2715245187282562,"y":0.2193697988986969,"z":-0.06361556798219681,"w":-0.934990644454956},"size":591.0577392578125,"orthographic":false}